AUTHORS
CHANGELOG.txt
DESCRIPTION
LICENSE
MANIFEST.in
README.rst
setup.cfg
setup.py
aps_bom/__init__.py
aps_bom/admin.py
aps_bom/forms.py
aps_bom/models.py
aps_bom/settings.py
aps_bom/urls.py
aps_bom/views.py
aps_bom/fixtures/bootstrap_aps_bom.json
aps_bom/fixtures/bootstrap_auth.json
aps_bom/migrations/0001_initial.py
aps_bom/migrations/0002_auto__add_field_cbomitem_cosign.py
aps_bom/migrations/0003_auto__del_field_bomitem_ipn__chg_field_bom_ipn__del_field_cbomitem_epn.py
aps_bom/migrations/0004_auto__add_field_bomitem_ipn__add_field_cbomitem_epn.py
aps_bom/migrations/0005_auto__del_field_ipn_price_max.py
aps_bom/migrations/0006_auto__add_field_ipn_code2.py
aps_bom/migrations/0007_auto__add_ipnmanager__add_field_cbomitem_unit_code__add_field_cbomitem.py
aps_bom/migrations/0008_auto__chg_field_cbomitem_position.py
aps_bom/migrations/0009_auto__add_technology__add_product__add_field_company_shipping_days__ad.py
aps_bom/migrations/__init__.py
aps_bom/static/.empty
aps_bom/static/aps_bom/.empty
aps_bom/static/aps_bom/cBOM_template.csv
aps_bom/static/aps_bom/cbom_admin.js
aps_bom/templates/admin/aps_bom/change_form.html
aps_bom/templates/aps_bom/.empty
aps_bom/templates/aps_bom/bom_upload.html
aps_bom/templates/aps_bom/cbom_download.html
aps_bom/templates/aps_bom/cbom_upload.html
aps_bom/templates/aps_bom/upload_base.html
aps_bom/tests/.coverage
aps_bom/tests/.coveragerc
aps_bom/tests/__init__.py
aps_bom/tests/factories.py
aps_bom/tests/forms_tests.py
aps_bom/tests/models_tests.py
aps_bom/tests/runtests.py
aps_bom/tests/south_settings.py
aps_bom/tests/test_settings.py
aps_bom/tests/urls.py
aps_bom/tests/views_tests.py
aps_bom/tests/files/BOM.csv
aps_bom/tests/files/cBOM.csv
aps_bom/tests/test_app/__init__.py
aps_bom/tests/test_app/models.py
aps_bom/tests/test_app/templates/400.html
aps_bom/tests/test_app/templates/500.html
aps_bom/tests/test_app/templates/base.html
django_aps_bom.egg-info/PKG-INFO
django_aps_bom.egg-info/SOURCES.txt
django_aps_bom.egg-info/dependency_links.txt
django_aps_bom.egg-info/requires.txt
django_aps_bom.egg-info/top_level.txt