Metadata-Version: 1.0
Name: django-aps-bom
Version: 0.6.3
Summary: The BOM module for django-apsara.
